module
proxy_bouncer
