Metadata-Version: 2.1
Name: proxy-bouncer
Version: 0.0.2
Summary: scraps proxys from an online list then returns and logs a list of valid and anon proxies
Home-page: https://github.com/deadlift1226/proxy_bouncer
Author: Dane Morgan
Author-email: danemorgan91@gmail.com
License: UNKNOWN
Platform: UNKNOWN
Classifier: Programming Language :: Python :: 3
Classifier: License :: OSI Approved :: MIT License
Classifier: Operating System :: OS Independent
